Workbook

Sheet Pipeline Flow (Simple KPI)
B1: PROPKART CRM — LEAD PIPELINE FLOW & KPI COUNTER
B2: Simplified Funnel: Leads In -> Telecaller Allocation -> Status -> Sales Handoff -> Closure • Real-Time Dynamic Date Filtering
B3: Select Timeframe Filter: | C3: This Week | D3: Active Filter Window: | E3: =TEXT(F4, "YYYY-MM-DD") & " to " & TEXT(G4, "YYYY-MM-DD") -> 2026-09-22 to 2026-09-28
B4: Available Filter Options: | C4: Dropdown choices in C3: [ All Time ] • [ Today ] • [ This Week ] • [ This Month ] • [ Custom Range ] | F4: =IF(C3="Today", DATE(2026,9,28), IF(C3="This Week", DATE(2026,9,22), IF(C3="This Month", DATE(2026,9,1), IF(C3="All Time", DATE(2020,1,1), C5)))) -> 46287 | G4: =IF(C3="Today", DATE(2026,9,28), IF(C3="This Week", DATE(2026,9,28), IF(C3="This Month", DATE(2026,9,28), IF(C3="All Time", DATE(2030,12,31), E5)))) -> 46293
B5: If 'Custom Range' selected: | C5: 46220 | D5: to | E5: 46293
B7: PIPELINE FLOW STAGE | C7: CURRENT KPI COUNT | D7: % SHARE / CONVERSION | E7: STAGE DESCRIPTION
B8: STAGE 1:HOW MANY LEADS GET IN
B9: Total leads we got | C9: =COUNTIFS(Requirement!$A:$A, ">="&$F$4, Requirement!$A:$A, "<="&$G$4+1) + COUNTIFS(Listing!$A:$A, ">="&$F$4, Listing!$A:$A, "<="&$G$4+1) -> 211 | D9: 100.0% | E9: Combined intake across all channels (Meta, Housing, Webhook, Direct)
B10: Requirement leads | C10: =COUNTIFS(Requirement!$A:$A, ">="&$F$4, Requirement!$A:$A, "<="&$G$4+1) -> 120 | D10: =IF($C$9>0, C10/$C$9, 0) -> 0.56872038 | E10: Clients looking to rent or buy property
B11: Listing leads | C11: =COUNTIFS(Listing!$A:$A, ">="&$F$4, Listing!$A:$A, "<="&$G$4+1) -> 91 | D11: =IF($C$9>0, C11/$C$9, 0) -> 0.43127962 | E11: Owners submitting property listings
B12: STAGE 2: TELECALLER ALLOCATION & QUEUE
B13: From total leads the allocation engine allocated leads | C13: =C9 - C14 -> 197 | D13: =IF($C$9>0, C13/$C$9, 0) -> 0.93364929 | E13: Inquiries assigned to active telecallers for calling
B14: Allocated but waiting in queue | C14: =COUNTIFS(Requirement!$A:$A, ">="&$F$4, Requirement!$A:$A, "<="&$G$4+1, Requirement!$E:$E, "Unassigned") + COUNTIFS(Listing!$A:$A, ">="&$F$4, Listing!$A:$A, "<="&$G$4+1, Listing!$E:$E, "Unassigned") -> 14 | D14: =IF($C$9>0, C14/$C$9, 0) -> 0.066350711 | E14: Awaiting telecaller assignment or direct intake
B15: STAGE 3: TELECALLER CALL OUTCOMES (WHAT IS ITS STATUS)
B16: • New / In Telecaller Calling Queue | C16: =COUNTIFS(Requirement!$A:$A, ">="&$F$4, Requirement!$A:$A, "<="&$G$4+1, Requirement!$F:$F, "New") + COUNTIFS(Listing!$A:$A, ">="&$F$4, Listing!$A:$A, "<="&$G$4+1, Listing!$F:$F, "New") -> 131 | D16: =IF($C$9>0, C16/$C$9, 0) -> 0.62085308 | E16: Assigned to telecaller, awaiting first call connect
B17: • Combined number of leads telecaller marked CNR | C17: =COUNTIFS(Requirement!$A:$A, ">="&$F$4, Requirement!$A:$A, "<="&$G$4+1, Requirement!$F:$F, "*CNR*") + COUNTIFS(Listing!$A:$A, ">="&$F$4, Listing!$A:$A, "<="&$G$4+1, Listing!$F:$F, "*CNR*") -> 10 | D17: =IF($C$9>0, C17/$C$9, 0) -> 0.047393365 | E17: Call placed; client phone rang or unanswered
B18: • Callback Scheduled | C18: =COUNTIFS(Requirement!$A:$A, ">="&$F$4, Requirement!$A:$A, "<="&$G$4+1, Requirement!$F:$F, "*Callback*") + COUNTIFS(Listing!$A:$A, ">="&$F$4, Listing!$A:$A, "<="&$G$4+1, Listing!$F:$F, "*Callback*") -> 3 | D18: =IF($C$9>0, C18/$C$9, 0) -> 0.014218009 | E18: Client requested follow-up at specific time
B19: • Interested | C19: =COUNTIFS(Requirement!$A:$A, ">="&$F$4, Requirement!$A:$A, "<="&$G$4+1, Requirement!$F:$F, "Interested") + COUNTIFS(Listing!$A:$A, ">="&$F$4, Listing!$A:$A, "<="&$G$4+1, Listing!$F:$F, "Interested") -> 1 | D19: =IF($C$9>0, C19/$C$9, 0) -> 0.0047393365 | E19: Client confirmed criteria; collecting preferences
B20: • Not interested | C20: =COUNTIFS(Requirement!$A:$A, ">="&$F$4, Requirement!$A:$A, "<="&$G$4+1, Requirement!$F:$F, "Rejected*") + COUNTIFS(Requirement!$A:$A, ">="&$F$4, Requirement!$A:$A, "<="&$G$4+1, Requirement!$F:$F, "Archived") + COUNTIFS(Listing!$A:$A, ">="&$F$4, Listing!$A:$A, "<="&$G$4+1, Listing!$F:$F, "Rejected*") -> 18 | D20: =IF($C$9>0, C20/$C$9, 0) -> 0.085308057 | E20: No requirement, budget/location mismatch, or wrong number
B21: • Verified & Listed on PropKart | C21: =COUNTIFS(Listing!$A:$A, ">="&$F$4, Listing!$A:$A, "<="&$G$4+1, Listing!$F:$F, "Listed*") -> 17 | D21: =IF($C$9>0, C21/$C$9, 0) -> 0.08056872 | E21: Owner inquiry verified and published live on portal
B22: STAGE 4: SALES TEAM ALLOCATION (THE 6 PEOPLE & PROPKART ADMIN)
B23: Total Qualified Leads Handed to Sales | C23: =COUNTIFS(Requirement!$A:$A, ">="&$F$4, Requirement!$A:$A, "<="&$G$4+1, Requirement!$G:$G, "<>Not Assigned") + COUNTIFS(Listing!$A:$A, ">="&$F$4, Listing!$A:$A, "<="&$G$4+1, Listing!$G:$G, "<>Not Assigned", Listing!$G:$G, "<>PropKart Direct") -> 50 | D23: =IF($C$9>0, C23/$C$9, 0) -> 0.23696682 | E23: Qualified leads assigned to Sales Executives
B24: • Rajan Purani | C24: =COUNTIFS(Requirement!$A:$A, ">="&$F$4, Requirement!$A:$A, "<="&$G$4+1, Requirement!$G:$G, "Rajan Purani") + COUNTIFS(Listing!$A:$A, ">="&$F$4, Listing!$A:$A, "<="&$G$4+1, Listing!$G:$G, "Rajan Purani") -> 8 | D24: =IF($C$23>0, C24/$C$23, 0) -> 0.16 | E24: Sales Team Lead • High-value requirement allocation
B25: • Rakesh Jadav | C25: =COUNTIFS(Requirement!$A:$A, ">="&$F$4, Requirement!$A:$A, "<="&$G$4+1, Requirement!$G:$G, "Rakesh Jadav") + COUNTIFS(Listing!$A:$A, ">="&$F$4, Listing!$A:$A, "<="&$G$4+1, Listing!$G:$G, "Rakesh Jadav") -> 15 | D25: =IF($C$23>0, C25/$C$23, 0) -> 0.3 | E25: Senior Sales • Key client portfolio management
B26: • Somel Rathod | C26: =COUNTIFS(Requirement!$A:$A, ">="&$F$4, Requirement!$A:$A, "<="&$G$4+1, Requirement!$G:$G, "Somel Rathod") + COUNTIFS(Listing!$A:$A, ">="&$F$4, Listing!$A:$A, "<="&$G$4+1, Listing!$G:$G, "Somel Rathod") -> 12 | D26: =IF($C$23>0, C26/$C$23, 0) -> 0.24 | E26: Senior Sales • Active client matching & property visits
B27: • Viral Jadeja | C27: =COUNTIFS(Requirement!$A:$A, ">="&$F$4, Requirement!$A:$A, "<="&$G$4+1, Requirement!$G:$G, "Viral Jadeja") + COUNTIFS(Listing!$A:$A, ">="&$F$4, Listing!$A:$A, "<="&$G$4+1, Listing!$G:$G, "Viral Jadeja") -> 9 | D27: =IF($C$23>0, C27/$C$23, 0) -> 0.18 | E27: Sales Executive • Client outreach & site visits
B28: • Prexa Vithalapara | C28: =COUNTIFS(Requirement!$A:$A, ">="&$F$4, Requirement!$A:$A, "<="&$G$4+1, Requirement!$E:$E, "Prexa Vithalapara") + COUNTIFS(Listing!$A:$A, ">="&$F$4, Listing!$A:$A, "<="&$G$4+1, Listing!$E:$E, "Prexa Vithalapara") -> 38 | D28: =IF($C$9>0, C28/$C$9, 0) -> 0.18009479 | E28: Core Telecaller • Inquiries processed
B29: • Zeel Mudaliyar | C29: =COUNTIFS(Requirement!$A:$A, ">="&$F$4, Requirement!$A:$A, "<="&$G$4+1, Requirement!$E:$E, "Zeel Mudaliyar") + COUNTIFS(Listing!$A:$A, ">="&$F$4, Listing!$A:$A, "<="&$G$4+1, Listing!$E:$E, "Zeel Mudaliyar") -> 150 | D29: =IF($C$9>0, C29/$C$9, 0) -> 0.71090047 | E29: Core Telecaller • Inquiries processed
B30: • Propkart Admin (Admin - Operations & Inventory) | C30: =COUNTIFS('Inventory (Total Properties)'!$A:$A, ">="&$F$4, 'Inventory (Total Properties)'!$A:$A, "<="&$G$4+1, 'Inventory (Total Properties)'!$Q:$Q, "Propkart Admin") -> 16 | D30: - | E30: System Admin • Direct CRM inventory creation & management
B31: STAGE 5: SALES PIPELINE OUTCOMES (CONVERSION & CLOSURE)
B32: • Assigned / In Active Follow-up & Discussion | C32: =COUNTIFS(Requirement!$A:$A, ">="&$F$4, Requirement!$A:$A, "<="&$G$4+1, Requirement!$H:$H, "*Follow*") + COUNTIFS(Requirement!$A:$A, ">="&$F$4, Requirement!$A:$A, "<="&$G$4+1, Requirement!$H:$H, "Interested") + COUNTIFS(Requirement!$A:$A, ">="&$F$4, Requirement!$A:$A, "<="&$G$4+1, Requirement!$H:$H, "Live") + COUNTIFS(Requirement!$A:$A, ">="&$F$4, Requirement!$A:$A, "<="&$G$4+1, Requirement!$H:$H, "Assigned*") -> 24 | D32: =IF($C$23>0, C32/$C$23, 0) -> 0.48 | E32: Clients in active discussions with sales team
B33: • Site Visits Scheduled | C33: =COUNTIFS(Requirement!$A:$A, ">="&$F$4, Requirement!$A:$A, "<="&$G$4+1, Requirement!$H:$H, "*Visit Scheduled*") -> 0 | D33: =IF($C$23>0, C33/$C$23, 0) -> 0 | E33: Physical property visits scheduled with client
B34: • Site Visits Completed / Done | C34: =COUNTIFS(Requirement!$A:$A, ">="&$F$4, Requirement!$A:$A, "<="&$G$4+1, Requirement!$H:$H, "*Visit Done*") -> 1 | D34: =IF($C$23>0, C34/$C$23, 0) -> 0.02 | E34: Physical walkthrough executed with sales executive
B35: Deals Won / Closed (Converted to Revenue) | C35: =COUNTIFS(Requirement!$A:$A, ">="&$F$4, Requirement!$A:$A, "<="&$G$4+1, Requirement!$H:$H, "*Won*") -> 0 | D35: =IF($C$23>0, C35/$C$23, 0) -> 0 | E35: Successfully closed rental / resale commercial deals
B36: • Disqualified / Rejected by Sales | C36: =COUNTIFS(Requirement!$A:$A, ">="&$F$4, Requirement!$A:$A, "<="&$G$4+1, Requirement!$H:$H, "Rejected*") + COUNTIFS(Requirement!$A:$A, ">="&$F$4, Requirement!$A:$A, "<="&$G$4+1, Requirement!$H:$H, "Disqualified*") -> 12 | D36: =IF($C$23>0, C36/$C$23, 0) -> 0.24 | E36: Inquiries closed by sales without deal conversion
B37: STAGE 6: PROPKART INVENTORY PORTFOLIO (TOTAL PROPERTIES)
B38: Total Properties in Inventory | C38: =COUNTIFS('Inventory (Total Properties)'!$A:$A, ">="&$F$4, 'Inventory (Total Properties)'!$A:$A, "<="&$G$4+1) -> 28 | D38: 100.0% | E38: Verified properties in PropKart inventory database
B39: • Available Properties (Ready for Matching) | C39: =COUNTIFS('Inventory (Total Properties)'!$A:$A, ">="&$F$4, 'Inventory (Total Properties)'!$A:$A, "<="&$G$4+1, 'Inventory (Total Properties)'!$G:$G, "Available") -> 24 | D39: =IF($C$38>0, C39/$C$38, 0) -> 0.85714286 | E39: Active properties ready for immediate tenant/buyer walkthrough
B40: • Rented Out Properties (Closed Deals) | C40: =COUNTIFS('Inventory (Total Properties)'!$A:$A, ">="&$F$4, 'Inventory (Total Properties)'!$A:$A, "<="&$G$4+1, 'Inventory (Total Properties)'!$G:$G, "Rented Out") -> 4 | D40: =IF($C$38>0, C40/$C$38, 0) -> 0.14285714 | E40: Leased properties closed on PropKart
B41: • Sold Out / Other Properties | C41: =COUNTIFS('Inventory (Total Properties)'!$A:$A, ">="&$F$4, 'Inventory (Total Properties)'!$A:$A, "<="&$G$4+1, 'Inventory (Total Properties)'!$G:$G, "Sold Out") + COUNTIFS('Inventory (Total Properties)'!$A:$A, ">="&$F$4, 'Inventory (Total Properties)'!$A:$A, "<="&$G$4+1, 'Inventory (Total Properties)'!$G:$G, "To Be Available") -> 0 | D41: =IF($C$38>0, C41/$C$38, 0) -> 0 | E41: Outright sales and properties under upcoming notice

Sheet Executive KPI Dashboard
A1: PROPKART CRM — EXECUTIVE KPI & TIME-SERIES WORKLOAD DASHBOARD
A2: Authoritative Hostinger Database Audit • All-Time: 17-Jul-2026 to 28-Sep-2026 (73 Days Active) • Generated on: 28-Sep-2026 06:13 PM IST
A4: 📅 INTERACTIVE DATE FILTER: | B4: From Date (YYYY-MM-DD): | C4: 46220 | D4: To Date (YYYY-MM-DD): | E4: 46293 | F4: Quick Presets: | G4: Today (28-Sep) | H4: This Week (22 to 28-Sep) | I4: This Month (Sep 2026)
A5: 💡 Operational Usage Guide: | B5: To filter by custom dates, edit cells C4 & E4. In data sheets (Listing, Requirement, Inventory), click Column A 'Date Filters' or Column B 'date filter' dropdown.
A7: =COUNTIFS(Requirement!$A:$A, ">="&$C$4, Requirement!$A:$A, "<="&$E$4+1) + COUNTIFS(Listing!$A:$A, ">="&$C$4, Listing!$A:$A, "<="&$E$4+1) -> 1215 | B7: =COUNTIFS(Requirement!$A:$A, ">="&$C$4, Requirement!$A:$A, "<="&$E$4+1) -> 735 | C7: =COUNTIFS(Listing!$A:$A, ">="&$C$4, Listing!$A:$A, "<="&$E$4+1) -> 480 | D7: =COUNTIFS('Inventory (Total Properties)'!$A:$A, ">="&$C$4, 'Inventory (Total Properties)'!$A:$A, "<="&$E$4+1) -> 144 | E7: 1136 | F7: 144 | G7: 3
A8: DYNAMIC TOTAL LEADS (Filtered Inquiries) | B8: DYNAMIC REQUIREMENTS (Tenant / Buyer Leads) | C8: DYNAMIC LISTINGS (Owner Listing Inquiries) | D8: DYNAMIC INVENTORY ADDED (Properties Added) | E8: TOTAL ALL-TIME LEADS (All Ingested Leads) | F8: ACTIVE LIVE INVENTORY (Total PropKart Portfolio) | G8: TOTAL DEALS WON (Converted to Revenue)
A10: 1. MULTI-TIMEFRAME EXECUTIVE PERFORMANCE SUMMARY (TODAY, WEEKLY, MONTHLY, YEARLY)
A11: Executive CRM Performance Metric | B11: Today (28-Sep) | C11: Weekly (Last 7 Days) | D11: Monthly (Sep 2026) | E11: Yearly / All-Time (2026) | F11: % of All-Time | G11: Operational Flow & Business Impact
A12: Total Leads Ingested | B12: 16 | C12: 252 | D12: 1089 | E12: 1136 | F12: 100.0% | G12: Unified ingestion across Meta, Housing, Webhook & Direct
A13: • Meta Ads (Facebook & Instagram) | B13: 12 | C13: 185 | D13: 798 | E13: 831 | F13: 73.2% | G13: Core paid social campaign performance
A14: • Webhook API (External Feeds) | B14: 2 | C14: 28 | D14: 114 | E14: 120 | F14: 10.6% | G14: Automated inbound campaign feeds
A15: • Housing.com (Pahal API Auto-Sync) | B15: 1 | C15: 23 | D15: 94 | E15: 98 | F15: 8.6% | G15: Automated portal synchronization
A16: • Direct / Manual CRM Entry | B16: 1 | C16: 16 | D16: 83 | E16: 86 | F16: 7.6% | G16: Walk-in inquiries and manual intake
A17: • Organic Social Media | B17: 0 | C17: 0 | D17: 0 | E17: 1 | F17: 0.1% | G17: Brand organic engagement
A18: Property Listing Inquiries | B18: 4 | C18: 94 | D18: 385 | E18: 402 | F18: 35.4% | G18: Landlord / property owner inquiries
A19: Client Requirement Inquiries | B19: 12 | C19: 158 | D19: 704 | E19: 734 | F19: 64.6% | G19: Tenant / commercial buyer inquiries
A20: Leads Allocated to Telecallers | B20: 15 | C20: 238 | D20: 865 | E20: 892 | F20: 78.5% | G20: Actively distributed to telecaller calling queues
A21: Unallocated Leads in Queue | B21: 1 | C21: 14 | D21: 224 | E21: 244 | F21: 21.5% | G21: Awaiting round-robin assignment or direct conversions
A22: Leads Handed Over to Sales Team | B22: 2 | C22: 43 | D22: 225 | E22: 274 | F22: 24.1% | G22: Qualified prospects transferred to Sales Executives
A23: Site Visits Officially Scheduled | B23: 0 | C23: 8 | D23: 31 | E23: 34 | F23: - | G23: Physical client property walkthroughs scheduled
... A27: TOTAL DATABASE INGESTION | B27: 16 | C27: 252 | D27: 1089 | E27: 1136 | F27: 100.0% | G27: Complete authoritative database accounting
A29: 2. KEY PERSONNEL PERFORMANCE MATRIX (THE 6 CORE TEAM MEMBERS & PROPKART ADMIN)
A30: Team Member Name | B30: Designation / CRM Role | C30: Today (28-Sep) | D30: Weekly (7 Days) | E30: Monthly (Sep) | F30: Yearly / Total | G30: Requirements | H30: Listings | I30: Current Pipeline Status & Key Conversion | J30: Properties in Inventory
A31: Viral Jadeja | B31: Sales Executive | C31: 1 | D31: 10 | E31: 21 | F31: 21 | G31: 19 | H31: 2 | I31: Active Sales • 21 Assigned • 1 Inventory Onboarded | J31: 1
A32: Prexa Vithalapara | B32: Telecaller | C32: 2 | D32: 43 | E32: 466 | F32: 466 | G32: 300 | H32: 166 | I32: Active Telecaller • 466 Allocated • High Volume Queue | J32: 2
A33: Zeel Mudaliyar | B33: Telecaller | C33: 13 | D33: 147 | E33: 426 | F33: 426 | G33: 231 | H33: 195 | I33: Active Telecaller • 426 Allocated • Lead Qualification Lead | J33: 6
A34: Somel Rathod | B34: Senior Sales Executive | C34: 0 | D34: 12 | E34: 50 | F34: 59 | G34: 55 | H34: 4 | I34: Active Sales • 59 Assigned • 23 Properties in Inventory | J34: 23
A35: Rakesh Jadav | B35: Senior Sales Executive | C35: 0 | D35: 13 | E35: 68 | F35: 86 | G35: 83 | H35: 3 | I35: Senior Sales • 86 Assigned • 33 Properties in Inventory | J35: 33
A36: Rajan Purani | B36: Sales Team Leader | C36: 1 | D36: 8 | E36: 86 | F36: 100 | G36: 97 | H36: 3 | I36: Sales Team Lead • 100 Assigned • 23 Properties in Inventory | J36: 23
A37: Propkart Admin | B37: Admin & Operations Lead | C37: 0 | D37: 0 | E37: 32 | F37: 64 | G37: 64 | H37: 0 | I37: System Admin • 30 Properties Added • 27 Site Visits Scheduled | J37: 30
A38: Daksh Jasoliya | B38: Telecaller / Field Support | C38: 0 | D38: 0 | E38: 0 | F38: 0 | G38: 0 | H38: 0 | I38: Registered Telecaller • 26 Properties Onboarded | J38: 26
A39: TOTAL KEY PERSONNEL WORKLOAD | B39: Core Team Total | C39: 17 | D39: 233 | E39: 1149 | F39: 1222 | G39: 849 | H39: 373 | I39: Full Core Team Workload Across All Departments | J39: 144
A41: 3. TELECALLER CALL OUTCOMES & DISPOSITIONS (TODAY, WEEKLY, MONTHLY, YEARLY)
A42: Telecaller Pipeline Outcome | B42: Today | C42: Weekly (7 Days) | D42: Monthly (Sep) | E42: Yearly / Total | F42: Listing Leads | G42: Requirement Leads | H42: Share (%) | I42: Next Operational Trigger
A43: New / Open (In Telecaller Queue) | B43: 10 | C43: 122 | D43: 356 | E43: 380 | F43: 204 | G43: 176 | H43: 33.5% | I43: Queued for immediate calling outreach
A44: CNR (Could Not Reach / Unanswered) | B44: 3 | C44: 52 | D44: 154 | E44: 163 | F44: 75 | G44: 88 | H44: 14.3% | I44: Retried across morning/evening calling slots
A45: Callback Scheduled | B45: 1 | C45: 7 | D45: 24 | E45: 26 | F45: 16 | G45: 10 | H45: 2.3% | I45: Calendar follow-up scheduled with client
A46: Interested (In Nurturing / Sourcing) | B46: 1 | C46: 38 | D46: 149 | E46: 158 | F46: 43 | G46: 115 | H46: 13.9% | I46: Collecting exact preferences for handoff
A47: Picked Up & Handed to Sales | B47: 1 | C47: 29 | D47: 144 | E47: 152 | F47: 10 | G47: 142 | H47: 13.4% | I47: Direct handoff to assigned sales executive
A48: Property Listed on PropKart | B48: 0 | C48: 4 | D48: 19 | E48: 21 | F48: 21 | G48: 0 | H48: 1.8% | I48: Verified owner inquiry published to portal
A49: Disqualified / Lost / Invalid | B49: 0 | C49: 43 | D49: 237 | E49: 278 | F49: 46 | G49: 232 | H49: 24.5% | I49: Archived with documented rejection reason
A50: TOTAL ALLOCATED LEADS | B50: 16 | C50: 252 | D50: 1089 | E50: 1136 | F50: 402 | G50: 734 | H50: 100.0% | I50: Authoritative telecaller pipeline distribution
A52: 4. SALES FUNNEL & STATUS TOGGLED BY SALES USERS (TODAY, WEEKLY, MONTHLY, YEARLY)
A53: Sales User Toggled Status | B53: Today | C53: Weekly (7 Days) | D53: Monthly (Sep) | E53: Yearly / Total | F53: Sales Stage | G53: Funnel Share | H53: Operational Meaning & Next Action
A54: Assigned / Open | B54: 1 | C54: 8 | D54: 28 | E54: 32 | F54: Stage 1: Intake | G54: 16.2% | H54: Lead transferred; awaiting first sales outreach
A55: Follow-up Scheduled | B55: 0 | C55: 3 | D55: 10 | E55: 12 | F55: Stage 2: Followup | G55: 6.1% | H55: Client active in discussion; follow-up scheduled
A56: Re-Followup (Extended) | B56: 0 | C56: 6 | D56: 26 | E56: 31 | F56: Stage 2: Followup | G56: 15.7% | H56: Multiple follow-ups; client evaluating options
A57: Interested (Active Search) | B57: 1 | C57: 4 | D57: 14 | E57: 16 | F57: Stage 3: Evaluation | G57: 8.1% | H57: Client shortlisted options; awaiting visit date
A58: Live (Active CRM Requirement) | B58: 0 | C58: 1 | D58: 5 | E58: 6 | F58: Stage 3: Evaluation | G58: 3.0% | H58: Active continuous search requirement in CRM
A59: Site Visits Pending / Scheduled | B59: 0 | C59: 8 | D59: 31 | E59: 34 | F59: Stage 4: Site Visit | G59: - | H59: Officially scheduled in CRM site_visits
A60: Site Visit Done / Completed | B60: 0 | C60: 1 | D60: 6 | E60: 7 | F60: Stage 4: Site Visit | G60: 3.6% | H60: Physical walkthrough completed; negotiation stage
A61: Deal Won / Closed | B61: 0 | C61: 0 | D61: 3 | E61: 3 | F61: Stage 5: Deal Won | G61: 1.5% | H61: Deal finalized and closed on PropKart
A62: Disqualified / Rejected | B62: 0 | C62: 12 | D62: 69 | E62: 82 | F62: Stage 6: Closed | G62: 41.6% | H62: Closed without conversion (detailed below)
A63: Not Started / Uncategorized | B63: 0 | C63: 1 | D63: 8 | E63: 9 | F63: Stage 1: Intake | G63: 4.6% | H63: Initial intake state awaiting first touchpoint
A64: TOTAL SALES PIPELINE | B64: 2 | C64: 43 | D64: 225 | E64: 274 | F64: Active Sales | G64: 100.0% | H64: Complete Sales Executive pipeline tracking
A66: 5. REJECTION REASON ANALYSIS (WHY WERE LEADS REJECTED BY SALES?)
A67: Rejection Reason Category | B67: Disqualified Count | C67: % of Disqualifications | D67: Detailed Root Cause Analysis | E67: Operational & Strategic Recommendation | F67: Campaign Optimization Action
A68: Rejected (No Requirement) | B68: 18 | C68: 22.0% | D68: Client stated they do not need any property at present | E68: Inquiry was accidental or curiosity click | F68: Refine ad copy to emphasize commitment
A69: Rejected (Budget Mismatch) | B69: 17 | C69: 20.7% | D69: Client budget is significantly below market rental rates | E69: Client expectations unrealistically low for locality | F69: Display starting prices clearly in ad creatives
A70: Rejected (Locality Mismatch) | B70: 11 | C70: 13.4% | D70: Client requested locations outside PropKart coverage | E70: Demand for non-serviced Ahmedabad micro-markets | F70: Geo-fence ad sets strictly to serviced zones
A71: Rejected (Already Rented) | B71: 10 | C71: 12.2% | D71: Client finalized alternative property before sales connect | E71: Response speed / turnaround time factor | F71: Reduce lead handoff latency from telecall to sales
A72: Rejected (Not Answering) | B72: 4 | C72: 4.9% | D72: Client repeatedly unresponsive across WhatsApp & calls | E72: Lead became unreachable after initial interest | F72: Send automated WhatsApp template with listings
A73: Rejected (Negotiation Failed) | B73: 2 | C73: 2.4% | D73: Landlord and tenant could not agree on rent/deposit | E73: Commercial gap between offer and asking rate | F73: Train sales on dispute resolution & structuring
A74: Rejected (Broker / Channel Partner) | B74: 1 | C74: 1.2% | D74: Lead turned out to be an external real estate broker | E74: Broker seeking co-brokerage or property access | F74: Add 'Are you a direct client or agent?' check
A75: Rejected (Others / Personal Reasons) | B75: 19 | C75: 23.2% | D75: Family relocation postponed, financing delay, etc. | E75: Personal client circumstances preventing move | F75: Tag for future re-engagement in 60-90 days
A76: TOTAL DISQUALIFIED INQUIRIES | B76: 82 | C76: 100.0% | D76: Complete Documentation of Disqualification Causes | E76: Full Transparency on Sales Disqualification Patterns | F76: Ongoing Lead Quality Feedback Loop
A78: 6. INVENTORY & TOTAL PROPERTIES OVERVIEW (PORTFOLIO ANALYSIS)
A79: Inventory Portfolio Segment | B79: Total Count | C79: Today | D79: Weekly (7 Days) | E79: Monthly (Sep) | F79: Yearly / All-Time | G79: Share (%) | H79: Portfolio Availability & Status Meaning
A80: Status: Available | B80: 127 | C80: 0 | D80: 18 | E80: 111 | F80: 127 | G80: 88.2% | H80: Active available properties ready for tenant/buyer matching
A81: Status: Rented Out | B81: 14 | C81: 0 | D81: 1 | E81: 13 | F81: 14 | G81: 9.7% | H81: Successfully leased properties closed on PropKart
A82: Status: Sold Out | B82: 2 | C82: 0 | D82: 1 | E82: 1 | F82: 2 | G82: 1.4% | H82: Successfully sold resale properties
A83: Status: To Be Available | B83: 1 | C83: 0 | D83: 0 | E83: 1 | F83: 1 | G83: 0.7% | H83: Upcoming vacancy under notice period
A84: Property Type: Flat / Apartment | B84: 112 | C84: 0 | D84: 16 | E84: 98 | F84: 112 | G84: 77.8% | H84: Residential high-rise & mid-rise inventory
A85: Property Type: Office | B85: 16 | C85: 0 | D85: 2 | E85: 14 | F85: 16 | G85: 11.1% | H85: Commercial office space inventory
A86: Property Type: Villa / Bungalow | B86: 8 | C86: 0 | D86: 1 | E86: 7 | F86: 8 | G86: 5.6% | H86: Independent luxury residential properties
A87: Property Type: Shop / Showroom | B87: 5 | C87: 0 | D87: 1 | E87: 4 | F87: 5 | G87: 3.5% | H87: Commercial retail properties
A88: Property Type: Farmhouse / Others | B88: 3 | C88: 0 | D88: 0 | E88: 3 | F88: 3 | G88: 2.1% | H88: Leisure and outlying land parcels
A89: Listing Type: Rent | B89: 142 | C89: 0 | D89: 20 | E89: 124 | F89: 142 | G89: 98.6% | H89: Rental property portfolio
A90: Listing Type: Re-Sale | B90: 2 | C90: 0 | D90: 0 | E90: 2 | F90: 2 | G90: 1.4% | H90: Outright resale property portfolio
A91: Onboarded by: Rakesh Jadav | B91: 33 | C91: 0 | D91: 2 | E91: 6 | F91: 33 | G91: 22.9% | H91: Senior Sales inventory onboarding
... A99: PORTFOLIO TOTAL PROPERTIES | B99: 144 | C99: 0 | D99: 20 | E99: 126 | F99: 144 | G99: 100.0% | H99: Total verified inventory in PropKart database

Sheet Listing
A1: date | B1: date filter | C1: lead source | D1: lead name | E1: allocated telecaller | F1: current status | G1: if assigned -- sales user name | H1: sales user toggled current status | I1: remarks
A2: 46293.653 | B2: 1. Today (28-Sep) | C2: Meta Ads (NB PropertyTech Rental Ad 0408) | D2: ब्राह्मण (6006452344) | E2: Zeel Mudaliyar | F2: New | G2: Not Assigned | H2: N/A (Not Assigned) | I2: -
A3: 46293.487 | B3: 1. Today (28-Sep) | C3: Meta Ads (NB PropertyTech Rental Ad 0408) | D3: Samim Khatri (9016894002) | E3: Zeel Mudaliyar | F3: New | G3: Not Assigned | H3: N/A (Not Assigned) | I3: -
A4: 46293.486 | B4: 1. Today (28-Sep) | C4: Webhook API (NB PropertyTech Rental Ad 0408) | D4: Samim Khatri (9016894002) | E4: Zeel Mudaliyar | F4: New | G4: Not Assigned | H4: N/A (Not Assigned) | I4: -
A5: 46293.321 | B5: 1. Today (28-Sep) | C5: Meta Ads (NB PropertyTech Rental Ad 0408) | D5: Anil Khatri (9429510554) | E5: Unassigned | F5: Listed | G5: Not Assigned | H5: N/A (Not Assigned) | I5: -
A6: 46293.32 | B6: 1. Today (28-Sep) | C6: Webhook API (NB PropertyTech Rental Ad 0408) | D6: Anil Khatri (9429510554) | E6: Zeel Mudaliyar | F6: Listed | G6: Not Assigned | H6: N/A (Not Assigned) | I6: -
A7: 46292.921 | B7: 2. This Week (Last 7 Days) | C7: Housing.com (Koba) | D7: Vivek Singh (owner) (9426372931) | E7: Zeel Mudaliyar | F7: New | G7: Not Assigned | H7: N/A (Not Assigned) | I7: -
A8: 46292.816 | B8: 2. This Week (Last 7 Days) | C8: Meta Ads (NB PropertyTech Rental Ad 0408) | D8: Geeta Khatri (8368098432) | E8: Zeel Mudaliyar | F8: New | G8: Not Assigned | H8: N/A (Not Assigned) | I8: -
A9: 46292.815 | B9: 2. This Week (Last 7 Days) | C9: Webhook API (NB PropertyTech Rental Ad 0408) | D9: Geeta Khatri (8368098432) | E9: Prexa Vithalapara | F9: New | G9: Not Assigned | H9: N/A (Not Assigned) | I9: -
A10: 46292.788 | B10: 2. This Week (Last 7 Days) | C10: Webhook API (NB PropertyTech Rental Ad 0408) | D10: Ashutosh Shingala (9737938603) | E10: Zeel Mudaliyar | F10: New | G10: Not Assigned | H10: N/A (Not Assigned) | I10: -
A11: 46292.721 | B11: 2. This Week (Last 7 Days) | C11: Meta Ads (NB PropertyTech Rental Ad 0408) | D11: Janvi Gandhi (7069793887) | E11: Zeel Mudaliyar | F11: New | G11: Not Assigned | H11: N/A (Not Assigned) | I11: -
A12: 46292.721 | B12: 2. This Week (Last 7 Days) | C12: Webhook API (NB PropertyTech Rental Ad 0408) | D12: Janvi Gandhi (7069793887) | E12: Zeel Mudaliyar | F12: New | G12: Not Assigned | H12: N/A (Not Assigned) | I12: -
A13: 46292.449 | B13: 2. This Week (Last 7 Days) | C13: Webhook API (NB PropertyTech Rental Ad 0408) | D13: Kiru (7572958316) | E13: Zeel Mudaliyar | F13: New | G13: Not Assigned | H13: N/A (Not Assigned) | I13: -
... A414: 46286.483 | B414: 3. This Month (Sep 2026) | C414: Direct Property / Walk-in | D414: Shashtrinagar - Jaimin Rathod (9016134877 | E414: Direct CRM Listing | F414: Listed on PropKart (Rented Out) | G414: Daksh Jasoliya | H414: Onboarded (Rented Out) | I414: -
A415: 46284.739 | B415: 3. This Month (Sep 2026) | C415: Direct Property / Walk-in | D415: testing property - kjdkcjas (1326568979 | E415: Direct CRM Listing | F415: Listed on PropKart (Available) | G415: Propkart Admin | H415: Onboarded (Available)
A416: 46284.695 | B416: 3. This Month (Sep 2026) | C416: Direct Property / Walk-in | D416: Shree Krishna Center, near Bank Of Baroda - Sunil Chaterjee (6353676023 | E416: Direct CRM Listing | F416: Listed on PropKart (Available) | G416: Zeel Mudaliyar | H416: Onboarded (Available) | I416: -
A417: 46284.677 | B417: 3. This Month (Sep 2026) | C417: Direct Property / Walk-in | D417: Aakash Residency - Bhadresh Solanki (9825005069 | E417: Direct CRM Listing | F417: Listed on PropKart (Available) | G417: Daksh Jasoliya | H417: Onboarded (Available) | I417: -
A418: 46284.668 | B418: 3. This Month (Sep 2026) | C418: Direct Property / Walk-in | D418: Shyamvilla Bungalows - Pratik bhai (9228121713 | E418: Direct CRM Listing | F418: Listed on PropKart (Available) | G418: Daksh Jasoliya | H418: Onboarded (Available) | I418: -
A419: 46284.448 | B419: 3. This Month (Sep 2026) | C419: Direct Property / Walk-in | D419: Shrifal Apartments Gota - Kishor bhai (9824940006 | E419: Direct CRM Listing | F419: Listed on PropKart (Rented Out) | G419: Somel Rathod | H419: Onboarded (Rented Out) | I419: -
A420: 46283.668 | B420: 3. This Month (Sep 2026) | C420: Direct Property / Walk-in | D420: Aroma Residency - Williams bhai (7096040390 | E420: Direct CRM Listing | F420: Listed on PropKart (Available) | G420: Rajan Purani | H420: Onboarded (Available) | I420: -
A421: 46282.727 | B421: 3. This Month (Sep 2026) | C421: Direct Property / Walk-in | D421: Goyal Mayfair - Vidhan bahi (9898779777 | E421: Direct CRM Listing | F421: Listed on PropKart (Available) | G421: Rajan Purani | H421: Onboarded (Available) | I421: -
A422: 46279.536 | B422: 3. This Month (Sep 2026) | C422: Direct Property / Walk-in | D422: saral privesh - Jagdish meen (9724176176 | E422: Direct CRM Listing | F422: Listed on PropKart (Available) | G422: Rakesh Jadav | H422: Onboarded (Available) | I422: -
A423: 46278.97 | B423: 3. This Month (Sep 2026) | C423: Direct Property / Walk-in | D423: Singapore - segsgdfg (1946758683 | E423: Direct CRM Listing | F423: Listed on PropKart (Available) | G423: Propkart Admin | H423: Onboarded (Available) | I423: cscscac
A424: 46275.79 | B424: 3. This Month (Sep 2026) | C424: Direct Property / Walk-in | D424: akash reccidency - SMITA MAM (9978937501 | E424: Direct CRM Listing | F424: Listed on PropKart (Available) | G424: Rakesh Jadav | H424: Onboarded (Available) | I424: -
A425: 46275.615 | B425: 3. This Month (Sep 2026) | C425: Direct Property / Walk-in | D425: Harmoni harikesh - Akhil Prajapati (8765432190 | E425: Direct CRM Listing | F425: Listed on PropKart (Available) | G425: Propkart Admin | H425: Onboarded (Available) | I425: ....
A426: 46274.789 | B426: 3. This Month (Sep 2026) | C426: Direct Property / Walk-in | D426: Devsshi fatania - Devshi bhai (9265488925 | E426: Direct CRM Listing | F426: Listed on PropKart (Available) | G426: Rakesh Jadav | H426: Onboarded (Available) | I426: -
A427: 46274.537 | B427: 3. This Month (Sep 2026) | C427: Direct Property / Walk-in | D427: nirgune rise - mahesh jagani | E427: Direct CRM Listing | F427: Listed on PropKart (Available) | G427: Rakesh Jadav | H427: Onboarded (Available) | I427: -
... A481: 46220.713 | B481: 4. This Year (2026) | C481: Direct Property / Walk-in | D481: La Habitat - GD Maghnani (9414394220 | E481: Direct CRM Listing | F481: Listed on PropKart (Available) | G481: Rajan Purani | H481: Onboarded (Available) | I481: monday call kari ne photos mate javu

Sheet Requirement
A1: date | B1: date filter | C1: lead source | D1: lead name | E1: allocated telecaller | F1: current status | G1: if assigned -- sales user name | H1: sales user toggled current status | I1: remarks
A2: 46293.759 | B2: 1. Today (28-Sep) | C2: Direct | D2: Vivek Singh (9426372931) | E2: Zeel Mudaliyar | F2: New | G2: Rajan Purani | H2: New | I2: Location - Motera, Koba, Raysan and nearby area, Bunglow with some outdoor space and parking preffered | CRM: Location - Motera, Koba, Raysan and nearby area, Bunglow with some outdoor space and parking preffered
A3: 46293.673 | B3: 1. Today (28-Sep) | C3: Meta Ads (NB PropertyTech Survey Ad 3108) | D3: Vensi Pokiya (9327036161) | E3: Zeel Mudaliyar | F3: New | G3: Not Assigned | H3: N/A (Not Assigned) | I3: -
A4: 46293.649 | B4: 1. Today (28-Sep) | C4: Meta Ads (NB PropertyTech Survey Ad 3108) | D4: Shashank Tatu (9879919438) | E4: Zeel Mudaliyar | F4: New | G4: Not Assigned | H4: N/A (Not Assigned) | I4: -
A5: 46293.575 | B5: 1. Today (28-Sep) | C5: Meta Ads (NB PropertyTech Survey Ad 3108) | D5: Devika Ck Devika (9173685744) | E5: Zeel Mudaliyar | F5: New | G5: Not Assigned | H5: N/A (Not Assigned) | I5: -
A6: 46293.556 | B6: 1. Today (28-Sep) | C6: Housing.com (Navrangpura) | D6: Vishwrajsinh Jadeja (9265422446) | E6: Zeel Mudaliyar | F6: Sales | G6: Viral Jadeja | H6: Assigned | I6: Transfer: SG Highway, Gota, Thaltej, Bopal, 400-500 sq ft, budget 25-30 K, Fully furnished, office commercial property | Transfer Note: SG Highway, Gota, Thaltej, Bopal, 400-500 sq ft, budget 25-30 K, Fully furnished, office commercial property | CRM: [Telecaller Key Points]: SG Highway, Gota, Thaltej, Bopal, 400-500 sq ft, budget 25-30 K, Fully furnished, office commercial property | [Telecaller Key Points]: SG Highway, Gota, Thaltej, Bopal, 400-500 sq ft, budget 25-30 K, Fully furnished, office commercial property | SG Highway, Gota, Thaltej, Bopal, 400-500 sq ft, budget 25-30 K, Fully furnished, office commercial property
A7: 46293.516 | B7: 1. Today (28-Sep) | C7: Meta Ads (NB PropertyTech Survey Ad 3108) | D7: Diva (7069336262) | E7: Zeel Mudaliyar | F7: New | G7: Not Assigned | H7: N/A (Not Assigned) | I7: -
A8: 46293.51 | B8: 1. Today (28-Sep) | C8: Housing.com (Naranpura) | D8: Vivek Karavadia (9512227740) | E8: Zeel Mudaliyar | F8: New | G8: Not Assigned | H8: N/A (Not Assigned) | I8: -
A9: 46293.456 | B9: 1. Today (28-Sep) | C9: Meta Ads (NB PropertyTech Survey Ad 3108) | D9: Vishal Jat (9111010777) | E9: Zeel Mudaliyar | F9: Sales | G9: Rajan Purani | H9: Assigned | I9: Transfer: Locations Gurukul, Ambawadi, Memnagar, Vastrapur, 2 BHK, for family, with 25K budget range, Semi furnished AC and Bed required, possession after 1 month | Transfer Note: Locations Gurukul, Ambawadi, Memnagar, Vastrapur, 2 BHK, for family, with 25K budget range, Semi furnished AC and Bed required, possession after 1 month | CRM: [Telecaller Key Points]: Locations Gurukul, Ambawadi, Memnagar, Vastrapur, 2 BHK, for family, with 25K budget range, Semi furnished AC and Bed required, possession after 1 month | [Telecaller Key Points]: Locations Gurukul, Ambawadi, Memnagar, Vastrapur, 2 BHK, for family, with 25K budget range, Semi furnished AC and Bed required, possession after 1 month | Locations Gurukul, Ambawadi, Memnagar, Vastrapur, 2 BHK, for family, with 25K budget range, Semi furnished AC and Bed required, possession after 1 month
A10: 46293.453 | B10: 1. Today (28-Sep) | C10: Meta Ads (NB PropertyTech Survey Ad 3108) | D10: Pradip Chotara (9712315547) | E10: Prexa Vithalapara | F10: New | G10: Not Assigned | H10: N/A (Not Assigned) | I10: -
A11: 46293.438 | B11: 1. Today (28-Sep) | C11: Housing.com (Nava Vadaj) | D11: Mital Bride Studio (8734876967) | E11: Zeel Mudaliyar | F11: New | G11: Not Assigned | H11: N/A (Not Assigned) | I11: -
A12: 46293.396 | B12: 1. Today (28-Sep) | C12: Housing.com (Nava Vadaj) | D12: V (7974797176) | E12: Zeel Mudaliyar | F12: New | G12: Not Assigned | H12: N/A (Not Assigned) | I12: -
A13: 46293.339 | B13: 1. Today (28-Sep) | C13: Meta Ads (NB PropertyTech Survey Ad 3108) | D13: Harvi Soni (8320454975) | E13: Prexa Vithalapara | F13: New | G13: Not Assigned | H13: N/A (Not Assigned) | I13: -
... A736: 46220.549 | B736: 4. This Year (2026) | C736: Direct / Manual | D736: Rajan (8200659030) | E736: Unassigned | F736: Sales | G736: Rajan Purani | H736: Live | I736: 3 bhk semi or fully furnished | Followup: Call him | CRM: 3 bhk semi or fully furnished | CRM Followup: Call him

Sheet Inventory (Total Properties)
A1: date | B1: date filter | C1: property code | D1: title | E1: property type | F1: listing type | G1: status | H1: rent / price (₹) | I1: deposit (₹) | J1: maintenance (₹) | K1: bedrooms | L1: carpet area (sq ft) | M1: locality / area | N1: city | O1: owner name | P1: owner mobile | Q1: created by (user) | R1: remarks
A2: 46291.689 | B2: 2. This Week (Last 7 Days) | C2: PR-1194 | D2: Signature Elena,B/h Sangath Prominence, opp. CBD Mall, Zundal | E2: Flat | F2: Rent | G2: Available | H2: 22000 | I2: 22000 | J2: 0 | K2: 3 | L2: 922 | M2: Zundal | N2: Ahmedabad | O2: Aval Barochia | P2: 8866706086 | Q2: Zeel Mudaliyar | R2: -
A3: 46291.59 | B3: 2. This Week (Last 7 Days) | C3: PR-1193 | D3: Aakash 2 | E3: Flat | F3: Rent | G3: Rented Out | H3: 33000 | I3: 66000 | J3: 1500 | K3: 2 | L3: - | M3: Vastrapur | N3: Ahmedabad | O3: Karan bhai | P3: 9510877481 | Q3: Rajan Purani | R3: -
A4: 46290.753 | B4: 2. This Week (Last 7 Days) | C4: PR-1192 | D4: Sangath 2 | E4: Rowhouse/Tenament | F4: Rent | G4: Available | H4: 35000 | I4: 70000 | J4: 0 | K4: 3 | L4: 1030 | M4: Motera | N4: Ahmedabad | O4: Vivek Shah | P4: 9904902525 | Q4: Propkart Admin | R4: Semi furnished, modular kitchen, basic accesories
A5: 46290.707 | B5: 2. This Week (Last 7 Days) | C5: PR-1191 | D5: Kameshwar elite 140 | E5: Flat | F5: Rent | G5: Available | H5: 45000 | I5: 90000 | J5: 0 | K5: 3 | L5: 1342 | M5: Bodakdev | N5: Ahmedabad | O5: Jignesh mandlecha | P5: 7990733327 | Q5: Propkart Admin | R5: curtain rod, modular kitchen, fan and lights, bird nett, exhaust fan in Bathroom and kichen, adani Gas line
A6: 46290.662 | B6: 2. This Week (Last 7 Days) | C6: PR-1190 | D6: Jasmine Green 1 | E6: Flat | F6: Rent | G6: Available | H6: 16000 | I6: 32000 | J6: 2250 | K6: 2 | L6: 608 | M6: Vaishnodevi | N6: Ahmedabad | O6: Hardik Nayak | P6: 9724409089 | Q6: Propkart Admin | R6: Semi furnished, modular kitchen, bed, basic accesories, gas line Maintenance 2250
A7: 46290.65 | B7: 2. This Week (Last 7 Days) | C7: PR-1189 | D7: Sahjanand Status Bungalow | E7: Bungalow | F7: Rent | G7: Rented Out | H7: 70000 | I7: 140000 | J7: 0 | K7: 4 | L7: 1643 | M7: Science city | N7: Ahmedabad | O7: Rajan Purani | P7: 8200659030 | Q7: Propkart Admin | R7: TV, Refrigerator, AC, Fully furnished
A8: 46290.636 | B8: 2. This Week (Last 7 Days) | C8: PR-1188 | D8: Ratnadeep Complex | E8: Flat | F8: Rent | G8: Available | H8: 40000 | I8: 80000 | J8: 0 | K8: 3 | L8: 1250 | M8: - | N8: Ahmedabad | O8: Pathik Brahmkshatriya | P8: 9727603446 | Q8: Propkart Admin | R8: Two Split ACs, Sofa (3+2), Dining Table with 4 Chairs, CNG Gas connection, Refrigerator, Furnished Kitchen with store room, Center table, Dressing Table, Wardrobes, Double bed with Mattresses, Temple Altar
A9: 46290.609 | B9: 2. This Week (Last 7 Days) | C9: PR-1187 | D9: Diwali Blessings | E9: Flat | F9: Rent | G9: Available | H9: 35000 | I9: 70000 | J9: 0 | K9: 3 | L9: 787 | M9: Vaishnodevi | N9: Ahmedabad | O9: Uma Vyas | P9: 7043336692 | Q9: Propkart Admin | R9: Furnished Kitchen, folding dining, TV, AC, Gyzer, Ro, Refridgerator, Washing machine, fully furnished
A10: 46290.598 | B10: 2. This Week (Last 7 Days) | C10: PR-1186 | D10: Shop Sagar Avenue | E10: Office | F10: Rent | G10: Available | H10: 13000 | I10: 26000 | J10: 0 | K10: 1 | L10: 110 | M10: Ashram Road | N10: Ahmedabad | O10: Pradeep Pithadiya | P10: 9016337978 | Q10: Propkart Admin | R10: -
A11: 46290.592 | B11: 2. This Week (Last 7 Days) | C11: PR-1185 | D11: Chandraprabhu Krupa Society | E11: Rowhouse/Tenament | F11: Rent | G11: Available | H11: 30000 | I11: 60000 | J11: 0 | K11: 3 | L11: 1417.5 | M11: Ranip | N11: Ahmedabad | O11: Parmeshwar | P11: 9265031372 | Q11: Propkart Admin | R11: Semi furnished, modular kitchen, basic accesories
A12: 46290.547 | B12: 2. This Week (Last 7 Days) | C12: PR-1184 | D12: Suyash Status , Near Capital 1 Science city | E12: Flat | F12: Rent | G12: Available | H12: 35000 | I12: 35000 | J12: 0 | K12: 3 | L12: 1400 | M12: Science city | N12: Ahmedabad | O12: Viral bhai | P12: 9016134878 | Q12: Propkart Admin | R12: Viral bhai ae aa property mokli che other details mate Viral bhai ne contact kro
A13: 46290.538 | B13: 2. This Week (Last 7 Days) | C13: PR-1183 | D13: Riverside park park, New Vasna | E13: Flat | F13: Rent | G13: Available | H13: 17000 | I13: 34000 | J13: 0 | K13: 2 | L13: 571 | M13: Vasna | N13: Ahmedabad | O13: Ashmita Patel | P13: 9510187511 | Q13: Propkart Admin | R13: Semi furnished, modular kitchen, bed, basic accesories
A14: 46290.534 | B14: 2. This Week (Last 7 Days) | C14: PR-1182 | D14: RJ Pashmina | E14: Flat | F14: Rent | G14: Available | H14: 35000 | I14: 35000 | J14: 0 | K14: 3 | L14: 1512 | M14: Chandkheda | N14: Ahmedabad | O14: Bhavik Kareliya | P14: 9824143858 | Q14: Propkart Admin | R14: -
A15: 46290.527 | B15: 2. This Week (Last 7 Days) | C15: PR-1181 | D15: MOONLIGHT COMPLEX OPP GURUKUL TEMPLE GURUKUL | E15: Shop | F15: Rent | G15: Available | H15: 11000 | I15: 22000 | J15: 0 | K15: 1 | L15: 117 | M15: Gurukul | N15: Ahmedabad | O15: Mukesh Jain | P15: 9638699860 | Q15: Propkart Admin | R15: -
... A19: 46290.492 | B19: 2. This Week (Last 7 Days) | C19: PR-1177 | D19: Shivranjni Society | E19: Rowhouse/Tenament | F19: Rent | G19: Available | H19: 25000 | I19: 50000 | J19: 333 | K19: 2 | L19: 600 | M19: Satellite | N19: Ahmedabad | O19: Ramesh Padia | P19: 9898467025 | Q19: Propkart Admin | R19: 4k per year, electricity bill excluded
A20: 46289.924 | B20: 2. This Week (Last 7 Days) | C20: PR-1176 | D20: shivanta regel zundal | E20: Flat | F20: Re-Sale | G20: Available | H20: 7500000 | I20: 0 | J20: 0 | K20: 3 | L20: - | M20: Vaishnodevi | N20: Ahmedabad | O20: karan bhai | P20: 9227087898 | Q20: Rakesh Jadav | R20: invester flate che sara rate ma
A21: 46289.787 | B21: 2. This Week (Last 7 Days) | C21: PR-1175 | D21: super city bhadaj | E21: Bungalow | F21: Rent | G21: Rented Out | H21: 39000 | I21: 78000 | J21: 4000 | K21: 4 | L21: 2000 | M21: Bhadaj | N21: Ahmedabad | O21: indu ben | P21: 9427132974 | Q21: Rakesh Jadav | R21: -
A22: 46289.69 | B22: 2. This Week (Last 7 Days) | C22: PR-1174 | D22: Daffodils PLAZA, Gala Gymkhana Road South Bopal | E22: Office | F22: Rent | G22: Available | H22: 30000 | I22: 30000 | J22: 0 | K22: 1 | L22: 594 | M22: South Bopal | N22: Ahmedabad | O22: Rajendra Jadav | P22: 9879160888 | Q22: Prexa Vithalapara | R22: 2 months deposit and pay advanvce rent every month
A23: 46289.619 | B23: 2. This Week (Last 7 Days) | C23: PR-1173 | D23: Suryansh Sanidhya Shivalaya, behind Sun Estate, near Ujala Cross road, Sarkhej, SG Highway, Ahmedabad | E23: Flat | F23: Rent | G23: Available | H23: 22000 | I23: 22000 | J23: 0 | K23: 2 | L23: 540 | M23: sarkhej | N23: Ahmedabad | O23: Girish Gohil | P23: 9909915052 | Q23: Zeel Mudaliyar | R23: -
A24: 46288.611 | B24: 2. This Week (Last 7 Days) | C24: PR-1172 | D24: Maher-5 | E24: Flat | F24: Rent | G24: Available | H24: 22000 | I24: 22000 | J24: 2000 | K24: 2 | L24: 659 | M24: Shela | N24: Ahmedabad | O24: Divyesh Ruparel | P24: 8306640345 | Q24: Daksh Jasoliya | R24: Semi furnished, modular kitchen, basic accesories, Geyser
A25: 46288.604 | B25: 2. This Week (Last 7 Days) | C25: PR-1171 | D25: Money plant high street | E25: Office | F25: Rent | G25: Available | H25: 45000 | I25: 45000 | J25: 0 | K25: 2 | L25: 355 | M25: - | N25: Ahmedabad | O25: Anil Mistry | P25: 9426569262 | Q25: Daksh Jasoliya | R25: Office furniture
A26: 46288.546 | B26: 2. This Week (Last 7 Days) | C26: PR-1170 | D26: GOYAL PALLADIUM | E26: Office | F26: Rent | G26: Available | H26: 43650 | I26: 87300 | J26: 2000 | K26: 1 | L26: 436 | M26: - | N26: Ahmedabad | O26: Nishita Shah | P26: 9427601721 | Q26: Daksh Jasoliya | R26: 2 AC, Partion Maintenance Charges separate
A27: 46288.477 | B27: 2. This Week (Last 7 Days) | C27: PR-1169 | D27: Mitri lake view | E27: Flat | F27: Rent | G27: Available | H27: 25000 | I27: 25000 | J27: 0 | K27: 2 | L27: 589 | M27: Zundal | N27: Ahmedabad | O27: Mamta Vora | P27: 8780327185 | Q27: Daksh Jasoliya | R27: -
A28: 46287.723 | B28: 2. This Week (Last 7 Days) | C28: PR-1168 | D28: Shivam Appartment | E28: Flat | F28: Rent | G28: Rented Out | H28: 15000 | I28: 15000 | J28: 200 | K28: 2 | L28: 888 | M28: New Vadaj | N28: Ahmedabad | O28: Dhaval Patel | P28: 9558630687 | Q28: Daksh Jasoliya | R28: Sofa, Double Bed, Dining table + warddrobe + 2 extra bed + modular kitchen, all fan + light + curtain + 2 AC point + 2 no water tank for water storage Maintenance 2500 annually
A29: 46287.494 | B29: 2. This Week (Last 7 Days) | C29: PR-1167 | D29: Pramukh park | E29: Flat | F29: Rent | G29: Available | H29: 27000 | I29: 27000 | J29: 0 | K29: 2 | L29: 810 | M29: Naranpura | N29: Ahmedabad | O29: Rajveet Singh | P29: 8264292166 | Q29: Daksh Jasoliya | R29: No Brokerage
A30: 46286.627 | B30: 3. This Month (Sep 2026) | C30: PR-1166 | D30: Madri Apartment | E30: Flat | F30: Rent | G30: Available | H30: 22000 | I30: 22000 | J30: 0 | K30: 2 | L30: 500 | M30: Memnagar | N30: Ahmedabad | O30: Umang Trivedi | P30: 9898426900 | Q30: Daksh Jasoliya | R30: -
A31: 46286.619 | B31: 3. This Month (Sep 2026) | C31: PR-1165 | D31: Sukun Arcade | E31: Office | F31: Rent | G31: Available | H31: 35000 | I31: 35000 | J31: 2800 | K31: 1 | L31: 487 | M31: Navrangpura | N31: Ahmedabad | O31: Viral Jani | P31: 9998526402 | Q31: Daksh Jasoliya | R31: Maintenance approx quarterly 8300
A32: 46286.551 | B32: 3. This Month (Sep 2026) | C32: PR-1164 | D32: Sun footprints | E32: Flat | F32: Rent | G32: Available | H32: 31000 | I32: 31000 | J32: 0 | K32: 2 | L32: 671 | M32: Shela | N32: Ahmedabad | O32: Raju Bharwad | P32: 6355323756 | Q32: Daksh Jasoliya | R32: Only vegetarian family
... A40: 46284.741 | B40: 3. This Month (Sep 2026) | C40: PR-1156 | D40: Setu Exotica | E40: Flat | F40: Rent | G40: Available | H40: 26500 | I40: 26500 | J40: 2500 | K40: 3 | L40: 1026 | M40: - | N40: Ahmedabad | O40: Dhairya Patel | P40: 8141279797 | Q40: Daksh Jasoliya | R40: 2500 maintenance
A41: 46284.739 | B41: 3. This Month (Sep 2026) | C41: PR-1155 | D41: testing property | E41: Flat | F41: Rent | G41: Available | H41: 13266 | I41: 39798 | J41: 0 | K41: 4 | L41: - | M41: - | N41: Ahmedabad | O41: kjdkcjas | P41: 1326568979 | Q41: Propkart Admin
A42: 46284.728 | B42: 3. This Month (Sep 2026) | C42: PR-1154 | D42: Savvy Studio | E42: Flat | F42: Rent | G42: Available | H42: 17000 | I42: 17000 | J42: 0 | K42: 1 | L42: 320 | M42: Gota | N42: Ahmedabad | O42: Chetan Ghediya | P42: 8734811158 | Q42: Zeel Mudaliyar | R42: Also Available for Bachelors
A43: 46284.695 | B43: 3. This Month (Sep 2026) | C43: PR-1153 | D43: Shree Krishna Center, near Bank Of Baroda | E43: Flat | F43: Rent | G43: Available | H43: 20000 | I43: 20000 | J43: 5000 | K43: 1 | L43: 170 | M43: Navrangpura | N43: Ahmedabad | O43: Sunil Chaterjee | P43: 6353676023 | Q43: Zeel Mudaliyar | R43: -
A44: 46284.677 | B44: 3. This Month (Sep 2026) | C44: PR-1152 | D44: Aakash Residency | E44: Flat | F44: Rent | G44: Available | H44: 24000 | I44: 24000 | J44: 0 | K44: 2 | L44: 463 | M44: Shela | N44: Ahmedabad | O44: Bhadresh Solanki | P44: 9825005069 | Q44: Daksh Jasoliya | R44: -
A45: 46284.668 | B45: 3. This Month (Sep 2026) | C45: PR-1151 | D45: Shyamvilla Bungalows | E45: Rowhouse/Tenament | F45: Rent | G45: Available | H45: 39000 | I45: 39000 | J45: 0 | K45: 3 | L45: 891 | M45: Sola | N45: Ahmedabad | O45: Pratik bhai | P45: 9228121713 | Q45: Daksh Jasoliya | R45: -
A46: 46284.666 | B46: 3. This Month (Sep 2026) | C46: PR-1150 | D46: Keshavbaag Capital Asopalav, Vastrapur | E46: Office | F46: Rent | G46: Available | H46: 18000 | I46: 18000 | J46: 0 | K46: 1 | L46: 675 | M46: Vastrapur | N46: Ahmedabad | O46: Mehul Soni | P46: 9904721565 | Q46: Zeel Mudaliyar | R46: -
A47: 46284.482 | B47: 3. This Month (Sep 2026) | C47: PR-1149 | D47: hvhighi | E47: Office | F47: Rent | G47: Available | H47: 100000 | I47: 200000 | J47: 0 | K47: 1 | L47: - | M47: Ambli | N47: Ahmedabad | O47: test | P47: 1234567890 | Q47: Viral Jadeja | R47: hbhi
A48: 46284.448 | B48: 3. This Month (Sep 2026) | C48: PR-1148 | D48: Shrifal Apartments Gota | E48: Flat | F48: Rent | G48: Rented Out | H48: 17200 | I48: 34400 | J48: 1200 | K48: 2 | L48: - | M48: Gota | N48: Ahmedabad | O48: Kishor bhai | P48: 9824940006 | Q48: Somel Rathod | R48: -
A49: 46283.668 | B49: 3. This Month (Sep 2026) | C49: PR-1147 | D49: Aroma Residency | E49: Flat | F49: Rent | G49: Available | H49: 35000 | I49: 70000 | J49: 1500 | K49: 3 | L49: - | M49: Vastrapur | N49: Ahmedabad | O49: Williams bhai | P49: 7096040390 | Q49: Rajan Purani | R49: -
A50: 46283.641 | B50: 3. This Month (Sep 2026) | C50: PR-1146 | D50: Basil Skyline, Vaishnodevi circle | E50: Office | F50: Rent | G50: Available | H50: 16000 | I50: 16000 | J50: 0 | K50: 3 | L50: 150 | M50: - | N50: Ahmedabad | O50: Priyal Bhatt | P50: 9408280355 | Q50: Daksh Jasoliya | R50: 17,000 + tax and maintenance
A51: 46283.61 | B51: 3. This Month (Sep 2026) | C51: PR-1145 | D51: Swatrantra Senani Nagar | E51: Rowhouse/Tenament | F51: Rent | G51: Available | H51: 16000 | I51: 16000 | J51: 0 | K51: 1 | L51: 450 | M51: Akhbarnagar | N51: Ahmedabad | O51: Ghanshyam B Jethva | P51: 9328112792 | Q51: Daksh Jasoliya | R51: AC, lights, fans, basic accesories Open terrace, open parking, for both family as well as 2 bach.
A52: 46283.591 | B52: 3. This Month (Sep 2026) | C52: PR-1144 | D52: Shivay Signature Elena, Opp, CBD Mall, Zundal | E52: Flat | F52: Rent | G52: Available | H52: 23000 | I52: 23000 | J52: 0 | K52: 3 | L52: 922 | M52: - | N52: Ahmedabad | O52: Devang Parekh | P52: 9978908306 | Q52: Daksh Jasoliya | R52: Garden facing
A53: 46283.574 | B53: 3. This Month (Sep 2026) | C53: PR-1143 | D53: Narhari Colony, Kankariya | E53: Rowhouse/Tenament | F53: Rent | G53: Available | H53: 45000 | I53: 45000 | J53: 0 | K53: 4 | L53: 1115 | M53: - | N53: Ahmedabad | O53: Jay | P53: 9157684624 | Q53: Daksh Jasoliya | R53: No maintenance, 100 sq yard scape at house front, on ground floor, all facilities, wants 1 year of agreement
A54: 46283.565 | B54: 3. This Month (Sep 2026) | C54: PR-1142 | D54: Aambaag,near koba circle 382421 | E54: Flat | F54: Rent | G54: Available | H54: 33000 | I54: 33000 | J54: 0 | K54: 4 | L54: 1575 | M54: - | N54: Ahmedabad | O54: Ashvin Patel | P54: 9428514992 | Q54: Daksh Jasoliya | R54: Modular Kitched, curtain, lights, fans, basic accessories Electricity and gas bill from tenant side, good amenities such as gym, game zone etc..
A55: 46283.531 | B55: 3. This Month (Sep 2026) | C55: PR-1141 | D55: Radhe greenz 2 bunglows, k raheja road, gandhinagar | E55: Bungalow | F55: Rent | G55: Available | H55: 55000 | I55: 55000 | J55: 0 | K55: 4 | L55: 1125 | M55: - | N55: Ahmedabad | O55: Mukesh Patel | P55: 9825063997 | Q55: Daksh Jasoliya | R55: Separate garden provided
A56: 46283.518 | B56: 3. This Month (Sep 2026) | C56: PR-1140 | D56: Skyrise, Nr, Sanchi heights | E56: Flat | F56: Rent | G56: Rented Out | H56: 38000 | I56: 38000 | J56: 0 | K56: 3 | L56: 922 | M56: - | N56: Ahmedabad | O56: Kirit Patel | P56: 9924026800 | Q56: Daksh Jasoliya | R56: -
A57: 46283.514 | B57: 3. This Month (Sep 2026) | C57: PR-1139 | D57: Vida by neela spaces, gift city, Gandhinagar | E57: Flat | F57: Rent | G57: Available | H57: 48000 | I57: 48000 | J57: 0 | K57: 3 | L57: 1120 | M57: - | N57: Ahmedabad | O57: Milan Vaghela | P57: 8511724035 | Q57: Daksh Jasoliya | R57: Possession is next year in january 2027
A58: 46283.449 | B58: 3. This Month (Sep 2026) | C58: PR-1138 | D58: Sun Footprints | E58: Flat | F58: Rent | G58: Available | H58: 25000 | I58: 25000 | J58: 0 | K58: 2 | L58: 671 | M58: Shela | N58: Ahmedabad | O58: Dhaval Solanki | P58: 7622989941 | Q58: Prexa Vithalapara | R58: "Modular kitchen, Folding Dining, Safety Door, Lights & fans, 2 Geysers, Another Basic Accessories"
A59: 46282.727 | B59: 3. This Month (Sep 2026) | C59: PR-1137 | D59: Goyal Mayfair | E59: Flat | F59: Rent | G59: Available | H59: 65000 | I59: 130000 | J59: 2000 | K59: 5 | L59: - | M59: Shyamal | N59: Ahmedabad | O59: Vidhan bahi | P59: 9898779777 | Q59: Rajan Purani | R59: -
A60: 46282.699 | B60: 3. This Month (Sep 2026) | C60: PR-1136 | D60: Goyal mayfair | E60: Flat | F60: Rent | G60: Available | H60: 65000 | I60: 130000 | J60: 0 | K60: 5 | L60: 1890 | M60: Shyamal | N60: Ahmedabad | O60: Rajan purani | P60: 8200659030 | Q60: Daksh Jasoliya | R60: PG system not allowed Bachelors not allowed
A61: 46279.536 | B61: 3. This Month (Sep 2026) | C61: PR-1135 | D61: saral privesh | E61: Flat | F61: Rent | G61: Available | H61: 16500 | I61: 33000 | J61: 0 | K61: 2 | L61: - | M61: Chandkheda | N61: Ahmedabad | O61: Jagdish meen | P61: 9724176176 | Q61: Rakesh Jadav | R61: -
A62: 46278.97 | B62: 3. This Month (Sep 2026) | C62: PR-1134 | D62: Singapore | E62: Flat | F62: Rent | G62: Available | H62: 15000 | I62: 30000 | J62: 0 | K62: 3 | L62: 13256 | M62: Ambawadi (Ahmedabad) | N62: Ahmedabad | O62: segsgdfg | P62: 1946758683 | Q62: Propkart Admin | R62: cscscac
A63: 46276.636 | B63: 3. This Month (Sep 2026) | C63: PR-1133 | D63: Neminath Krupa Soceity | E63: Flat | F63: Rent | G63: Available | H63: 25000 | I63: 25000 | J63: 0 | K63: 2 | L63: 500 | M63: Memnagar | N63: Ahmedabad | O63: Saudamini Kapasi | P63: 6355275700 | Q63: Propkart Admin | R63: -
A64: 46276.624 | B64: 3. This Month (Sep 2026) | C64: PR-1132 | D64: Signor Skyline | E64: Flat | F64: Rent | G64: Available | H64: 25000 | I64: 25000 | J64: 0 | K64: 3 | L64: 922 | M64: Tragad | N64: Ahmedabad | O64: Prakash Dulera | P64: 7984420730 | Q64: Propkart Admin | R64: -
A65: 46276.601 | B65: 3. This Month (Sep 2026) | C65: PR-1131 | D65: Shivanta rigel | E65: Flat | F65: Rent | G65: Available | H65: 23000 | I65: 23000 | J65: 0 | K65: 3 | L65: 877 | M65: Vaishnodevi | N65: Ahmedabad | O65: Naresh Thakkar | P65: 9427645123 | Q65: Propkart Admin | R65: -
A66: 46276.595 | B66: 3. This Month (Sep 2026) | C66: PR-1130 | D66: Aristo Anandam | E66: Flat | F66: Rent | G66: Available | H66: 55000 | I66: 55000 | J66: 0 | K66: 2 | L66: 625 | M66: Tragad | N66: Ahmedabad | O66: Krishna Vitthalani | P66: 9376607294 | Q66: Propkart Admin | R66: -
A67: 46275.79 | B67: 3. This Month (Sep 2026) | C67: PR-1129 | D67: akash reccidency | E67: Flat | F67: Rent | G67: Available | H67: 21000 | I67: 42000 | J67: 0 | K67: 2 | L67: - | M67: Shela | N67: Ahmedabad | O67: SMITA MAM | P67: 9978937501 | Q67: Rakesh Jadav | R67: -
A68: 46275.695 | B68: 3. This Month (Sep 2026) | C68: PR-1128 | D68: Nirgun rise | E68: Flat | F68: Rent | G68: Available | H68: 28000 | I68: 28000 | J68: 0 | K68: 3 | L68: 1650 | M68: Shilaj | N68: Ahmedabad | O68: Mahesh Jesani | P68: 9904958998 | Q68: Propkart Admin | R68: -
A69: 46275.615 | B69: 3. This Month (Sep 2026) | C69: PR-1127 | D69: Harmoni harikesh | E69: Flat | F69: Rent | G69: Available | H69: 35000 | I69: 105000 | J69: 3000 | K69: 3 | L69: 3000 | M69: Ambawadi (Ahmedabad) | N69: Ahmedabad | O69: Akhil Prajapati | P69: 8765432190 | Q69: Propkart Admin | R69: ....
A70: 46274.789 | B70: 3. This Month (Sep 2026) | C70: PR-1126 | D70: Devsshi fatania | E70: Flat | F70: Rent | G70: Available | H70: 27000 | I70: 54000 | J70: 0 | K70: 2 | L70: - | M70: Ambawadi (Ahmedabad) | N70: Ahmedabad | O70: Devshi bhai | P70: 9265488925 | Q70: Rakesh Jadav | R70: -
A71: 46274.635 | B71: 3. This Month (Sep 2026) | C71: PR-1125 | D71: Panache | E71: Flat | F71: Rent | G71: Available | H71: 90000 | I71: 180000 | J71: 0 | K71: 4 | L71: - | M71: Vaishnodevi | N71: Ahmedabad | O71: Badresh Shah | P71: 9824430208 | Q71: Propkart Admin | R71: -
A72: 46274.537 | B72: 3. This Month (Sep 2026) | C72: PR-1124 | D72: nirgune rise | E72: Flat | F72: Rent | G72: Available | H72: 28000 | I72: 56000 | J72: 0 | K72: 3 | L72: 769 | M72: Shilaj | N72: Ahmedabad | O72: mahesh jagani | P72: - | Q72: Rakesh Jadav | R72: -
A73: 46273.591 | B73: 3. This Month (Sep 2026) | C73: PR-1123 | D73: testing properties only test purpose | E73: Flat | F73: Rent | G73: Available | H73: 35000 | I73: 70000 | J73: 3000 | K73: 2 | L73: 3245 | M73: Science city | N73: Ahmedabad | O73: Major Iqbal | P73: 1986532740 | Q73: Propkart Admin | R73: ewgbdsbckdsbckdbskjbcds DCONDWKJCNWDKL MCKJNDSKJCNSDKDSCDSCDS SVDSV CDCC GBGFRB BBV fbdfv
A74: 46272.523 | B74: 3. This Month (Sep 2026) | C74: PR-1122 | D74: 31 five zavery realty | E74: Office | F74: Rent | G74: Available | H74: 33000 | I74: 66000 | J74: 0 | K74: 1 | L74: - | M74: Prahladnagar | N74: Ahmedabad | O74: Atul Bhatt | P74: 9372061162 | Q74: Rajan Purani | R74: -
A75: 46272.508 | B75: 3. This Month (Sep 2026) | C75: PR-1121 | D75: Parshwa Towers | E75: Office | F75: Rent | G75: Available | H75: 45000 | I75: 45000 | J75: 0 | K75: 1 | L75: 1800 | M75: Bodakdev | N75: Ahmedabad | O75: Darshan | P75: 9979786654 | Q75: Propkart Admin | R75: "1 Boss cabin 2 cubicle 10 to 15 work station Pantry"
A76: 46269.674 | B76: 3. This Month (Sep 2026) | C76: PR-1120 | D76: festival o2 | E76: Flat | F76: Rent | G76: Rented Out | H76: 26000 | I76: 52000 | J76: 3000 | K76: 3 | L76: - | M76: Gota | N76: Ahmedabad | O76: RAJAN | P76: 6357993704 | Q76: Rajan Purani | R76: -
A77: 46268.544 | B77: 3. This Month (Sep 2026) | C77: PR-1119 | D77: Vandematram Prime | E77: Penthouse | F77: Rent | G77: Available | H77: 30000 | I77: 60000 | J77: 0 | K77: 2 | L77: - | M77: Gota | N77: Ahmedabad | O77: Piyush bhai patel | P77: 9998249086 | Q77: Somel Rathod | R77: -
A78: 46268.534 | B78: 3. This Month (Sep 2026) | C78: PR-1118 | D78: Sparsh Residency | E78: Flat | F78: Rent | G78: Rented Out | H78: 25000 | I78: 50000 | J78: 0 | K78: 3 | L78: - | M78: Science city | N78: Ahmedabad | O78: Neha Patel | P78: 8200935288 | Q78: Somel Rathod | R78: -
A79: 46268.524 | B79: 3. This Month (Sep 2026) | C79: PR-1117 | D79: Harsh Icon Shilaj | E79: Flat | F79: Rent | G79: Available | H79: 28000 | I79: 56000 | J79: 0 | K79: 3 | L79: - | M79: Shilaj | N79: Ahmedabad | O79: Rajesh Adroja | P79: 9998441037 | Q79: Somel Rathod | R79: -
A80: 46267.731 | B80: 3. This Month (Sep 2026) | C80: PR-1116 | D80: 501 The Green Parmeshwar | E80: Flat | F80: Rent | G80: To Be Available | H80: 20000 | I80: 40000 | J80: 2000 | K80: 2 | L80: - | M80: jagatpur | N80: Ahmedabad | O80: Abhishek panchal | P80: 9998875556 | Q80: Somel Rathod | R80: -
A81: 46265.705 | B81: 4. This Year (2026) | C81: PR-1115 | D81: Shilaj Enclave | E81: Flat | F81: Rent | G81: Available | H81: 25000 | I81: 50000 | J81: 0 | K81: 2 | L81: - | M81: Shilaj | N81: Ahmedabad | O81: Harshaida Vaghela | P81: 7046104905 | Q81: Rajan Purani | R81: -
A82: 46263.449 | B82: 4. This Year (2026) | C82: PR-1113 | D82: Sun Real Homes, New Ranip | E82: Flat | F82: Rent | G82: Rented Out | H82: 19000 | I82: 38000 | J82: 2000 | K82: 2 | L82: - | M82: New Ranip | N82: Ahmedabad | O82: Narendra bhai | P82: 9898345029 | Q82: Somel Rathod | R82: -
A83: 46261.495 | B83: 4. This Year (2026) | C83: PR-1112 | D83: Shaligram lakeview | E83: Flat | F83: Rent | G83: Available | H83: 26000 | I83: 52000 | J83: 0 | K83: 2 | L83: - | M83: Vaishnodevi | N83: Ahmedabad | O83: bhirma | P83: 9819729232 | Q83: Somel Rathod | R83: -
A84: 46261.474 | B84: 4. This Year (2026) | C84: PR-1111 | D84: Magnate lifestyle | E84: Flat | F84: Rent | G84: Available | H84: 18500 | I84: 37000 | J84: 2500 | K84: 2 | L84: - | M84: Vaishnodevi | N84: Ahmedabad | O84: Babubhai Patel | P84: 9909795304 | Q84: Somel Rathod | R84: -
A85: 46261.45 | B85: 4. This Year (2026) | C85: PR-1110 | D85: Keshar Samruddham | E85: Flat | F85: Rent | G85: Available | H85: 18500 | I85: 37000 | J85: 0 | K85: 2 | L85: - | M85: Vaishnodevi | N85: Ahmedabad | O85: sneha | P85: 9998865670 | Q85: Somel Rathod | R85: -
A86: 46260.695 | B86: 4. This Year (2026) | C86: PR-1109 | D86: Dev Parijat | E86: Flat | F86: Rent | G86: Available | H86: 25000 | I86: 50000 | J86: 1000 | K86: 3 | L86: - | M86: Vaishnodevi | N86: Ahmedabad | O86: Nitin Patel | P86: 9727080045 | Q86: Rajan Purani | R86: -
A87: 46260.656 | B87: 4. This Year (2026) | C87: PR-1108 | D87: Silver Nest | E87: Flat | F87: Rent | G87: Available | H87: 21000 | I87: 42000 | J87: 1000 | K87: 2 | L87: - | M87: Gota | N87: Ahmedabad | O87: Ramesh Bhai | P87: 9978538788 | Q87: Rajan Purani | R87: -
... A90: 46256.467 | B90: 4. This Year (2026) | C90: PR-1105 | D90: Black Buck Century | E90: Plot | F90: Re-Sale | G90: Available | H90: 1500000 | I90: 0 | J90: 0 | K90: 1 | L90: - | M90: Dholera city | N90: Ahmedabad | O90: Sanjeev Sir | P90: 6357993707 | Q90: Rajan Purani | R90: -
A91: 46255.672 | B91: 4. This Year (2026) | C91: PR-1104 | D91: Arise vibrant | E91: Flat | F91: Rent | G91: Available | H91: 30000 | I91: 60000 | J91: 0 | K91: 3 | L91: 769 | M91: Vaishnodevi | N91: Ahmedabad | O91: khemraj bhai rajwadi tea | P91: 9511545048 | Q91: Rakesh Jadav | R91: -
A92: 46255.519 | B92: 4. This Year (2026) | C92: PR-1103 | D92: Satellite complex, Mansi Circle | E92: Flat | F92: Rent | G92: Rented Out | H92: 25000 | I92: 25000 | J92: 0 | K92: 2 | L92: - | M92: Vastrapur | N92: Ahmedabad | O92: Rajendra Jain | P92: 9426702573 | Q92: Propkart Admin | R92: -
A93: 46254.555 | B93: 4. This Year (2026) | C93: PR-1100 | D93: SUHAAL SERENITY- Zundal | E93: Flat | F93: Rent | G93: Available | H93: 22000 | I93: 44000 | J93: 0 | K93: 3 | L93: - | M93: - | N93: Ahmedabad | O93: Paritosh bhai | P93: 9725931331 | Q93: Somel Rathod | R93: -
A94: 46254.515 | B94: 4. This Year (2026) | C94: PR-1099 | D94: B/16 Dev city | E94: Bungalow | F94: Rent | G94: Available | H94: 25000 | I94: 50000 | J94: 0 | K94: 3 | L94: - | M94: - | N94: Ahmedabad | O94: Sejal Ben | P94: 6357105011 | Q94: Somel Rathod | R94: -
A95: 46254.434 | B95: 4. This Year (2026) | C95: PR-1098 | D95: pacifica north enclave | E95: Flat | F95: Rent | G95: Available | H95: 27000 | I95: 54000 | J95: 0 | K95: 3 | L95: 765 | M95: Vaishnodevi | N95: Ahmedabad | O95: maulik dave | P95: 9054689316 | Q95: Rakesh Jadav | R95: -
A96: 46253.685 | B96: 4. This Year (2026) | C96: PR-1094 | D96: Elite Mercury | E96: Flat | F96: Rent | G96: Available | H96: 22500 | I96: 45000 | J96: 2500 | K96: 2 | L96: - | M96: Gota | N96: Ahmedabad | O96: krishna ben | P96: 8733910895 | Q96: Somel Rathod | R96: -
A97: 46253.502 | B97: 4. This Year (2026) | C97: PR-1093 | D97: Palm glory 4 | E97: Flat | F97: Rent | G97: Rented Out | H97: 42000 | I97: 84000 | J97: 0 | K97: 3 | L97: 970 | M97: Science city | N97: Ahmedabad | O97: Aryan | P97: 8866329054 | Q97: Rakesh Jadav | R97: -
A98: 46251.518 | B98: 4. This Year (2026) | C98: PR-1092 | D98: pearl heights | E98: Flat | F98: Rent | G98: Available | H98: 17500 | I98: 35000 | J98: 1800 | K98: 2 | L98: - | M98: Ghatlodia | N98: Ahmedabad | O98: hitendra bhai | P98: 9924006250 | Q98: Somel Rathod | R98: -
A99: 46251.511 | B99: 4. This Year (2026) | C99: PR-1091 | D99: kuber residency | E99: Flat | F99: Rent | G99: Available | H99: 17000 | I99: 34000 | J99: 2000 | K99: 2 | L99: - | M99: Bhadaj | N99: Ahmedabad | O99: Amit | P99: 9428411335 | Q99: Somel Rathod | R99: -
A100: 46251.458 | B100: 4. This Year (2026) | C100: PR-1090 | D100: Savvy swaraj | E100: Flat | F100: Rent | G100: Available | H100: 55000 | I100: 110000 | J100: 2500 | K100: 3 | L100: - | M100: Gota | N100: Ahmedabad | O100: Raxit Shah | P100: 9974051143 | Q100: Rajan Purani | R100: -
A101: 46251.444 | B101: 4. This Year (2026) | C101: PR-1089 | D101: Shyam Villa Bungalow | E101: Bungalow | F101: Rent | G101: Rented Out | H101: 40000 | I101: 80000 | J101: 2000 | K101: 3 | L101: - | M101: - | N101: Ahmedabad | O101: lalu desai | P101: 7621981297 | Q101: Rajan Purani | R101: -
A102: 46251.435 | B102: 4. This Year (2026) | C102: PR-1088 | D102: Falak Citadel | E102: Flat | F102: Rent | G102: Available | H102: 35000 | I102: 70000 | J102: 2000 | K102: 3 | L102: - | M102: - | N102: Ahmedabad | O102: Maulik pandya | P102: 7623017858 | Q102: Rajan Purani | R102: -
A103: 46249.035 | B103: 4. This Year (2026) | C103: PR-1086 | D103: Testing Property | E103: Flat | F103: Rent | G103: Available | H103: 55000 | I103: 110000 | J103: 5000 | K103: 5 | L103: 2653 | M103: Science park | N103: Ahmedabad | O103: Akhil Prajapati | P103: 1653298740 | Q103: Propkart Admin | R103: -
A104: 46248.507 | B104: 4. This Year (2026) | C104: PR-1083 | D104: Nirman Homes | E104: Flat | F104: Rent | G104: Available | H104: 20000 | I104: 40000 | J104: 2000 | K104: 2 | L104: - | M104: Gota | N104: Ahmedabad | O104: Kalpesh bhai | P104: 9879607282 | Q104: Rajan Purani | R104: -
A105: 46247.791 | B105: 4. This Year (2026) | C105: PR-1082 | D105: silver rediance 2 | E105: Showroom | F105: Re-Sale | G105: Available | H105: 24000000 | I105: 0 | J105: 0 | K105: 1 | L105: - | M105: - | N105: Ahmedabad | O105: ajay bhai | P105: 8780678133 | Q105: Rakesh Jadav | R105: -
A106: 46247.788 | B106: 4. This Year (2026) | C106: PR-1081 | D106: sanskrit galaria | E106: Showroom | F106: Re-Sale | G106: Available | H106: 30000000 | I106: 0 | J106: 0 | K106: 1 | L106: - | M106: Memnagar | N106: Ahmedabad | O106: Paresh parmar | P106: 9714784630 | Q106: Rakesh Jadav | R106: -
A107: 46247.674 | B107: 4. This Year (2026) | C107: PR-1080 | D107: sun siara bhadaj | E107: Flat | F107: Re-Sale | G107: Available | H107: 9200000 | I107: 0 | J107: 0 | K107: 3 | L107: 890 | M107: - | N107: Ahmedabad | O107: Narendra | P107: 9909289068 | Q107: Rakesh Jadav | R107: -
A108: 46247.55 | B108: 4. This Year (2026) | C108: PR-1077 | D108: Jivraj Park Society | E108: Flat | F108: Rent | G108: Rented Out | H108: 30000 | I108: 60000 | J108: 1500 | K108: 2 | L108: - | M108: Naranpura | N108: Ahmedabad | O108: Gunjan Soni | P108: 8160455535 | Q108: Rajan Purani | R108: -
A109: 46247.549 | B109: 4. This Year (2026) | C109: PR-1076 | D109: veer savarkar 1 | E109: Flat | F109: Re-Sale | G109: Available | H109: 4100000 | I109: 0 | J109: 0 | K109: 3 | L109: 700 | M109: Gota | N109: Ahmedabad | O109: Umesh bhai | P109: 8320296774 | Q109: Rakesh Jadav | R109: -
A110: 46247.548 | B110: 4. This Year (2026) | C110: PR-1075 | D110: veer savarkar 1 | E110: Flat | F110: Rent | G110: Available | H110: 15000 | I110: 30000 | J110: 0 | K110: 3 | L110: - | M110: Gota | N110: Ahmedabad | O110: Umesh bhai | P110: 8320296774 | Q110: Rakesh Jadav | R110: -
A111: 46247.523 | B111: 4. This Year (2026) | C111: PR-1074 | D111: rewa gift city | E111: Flat | F111: Rent | G111: Available | H111: 50000 | I111: 100000 | J111: 3000 | K111: 2 | L111: - | M111: Gandhinagar | N111: Ahmedabad | O111: Milan vaghela | P111: 8511724035 | Q111: Rajan Purani | R111: -
A112: 46246.681 | B112: 4. This Year (2026) | C112: PR-1073 | D112: Arise Vibrant | E112: Flat | F112: Rent | G112: Available | H112: 35000 | I112: 70000 | J112: 0 | K112: 3 | L112: - | M112: Vaishnodevi | N112: Ahmedabad | O112: Bharatkumar Somabhai Modi | P112: 9825503818 | Q112: Somel Rathod | R112: -
...
